[{
    "type": "Article",
    "title": "Hello World",
    "date": "2016/10/21",
    "content": "你好，世界11111111111111111"
  },
  {
    "type": "Article",
    "title": "Hello World",
    "date": "2016/10/21",
    "content": "你好，世界222222222222222"
  },
  {
    "type": "Article",
    "title": "Hello World",
    "date": "2016/10/21",
    "content": "你好，世界33333333333333333"
  }, {
    "type": "Article",
    "title": "Hello World",
    "date": "2016/10/21",
    "content": "你好，世界444444444444"
  }, {
    "type": "Article",
    "title": "Hello World",
    "date": "2016/10/21",
    "content": "你好，世界555555555555"
  }, {
    "type": "Article",
    "title": "Hello World",
    "date": "2016/10/21",
    "content": "你好，世界66666666666666666"
  }, {
    "type": "Article",
    "title": "Hello World",
    "date": "2016/10/21",
    "content": "你好，世界677777777777777777!"
  }, {
    "type": "Article",
    "title": "Hello World",
    "date": "2016/10/21",
    "content": "你好，世界!888888888888888"
  }, {
    "type": "Article",
    "title": "Hello World",
    "date": "2016/10/21",
    "content": "你好，世界9999999999999!"
  }, {
    "type": "Article",
    "title": "Hello World",
    "date": "2016/10/21",
    "content": "你好，世界10010101010010101!"
  }, {
    "type": "Article",
    "title": "Hello World",
    "date": "2016/10/21",
    "content": "你好，世界!"
  }, {
    "type": "Article",
    "title": "Hello World",
    "date": "2016/10/21",
    "content": "你好，世界!"
  }, {
    "type": "Article",
    "title": "Hello World",
    "date": "2016/10/21",
    "content": "你好，世界!"
  }, {
    "type": "Article",
    "title": "Hello World",
    "date": "2016/10/21",
    "content": "你好，世界!"
  }, {
    "type": "Article",
    "title": "Hello World",
    "date": "2016/10/21",
    "content": "你好，世界!"
  }, {
    "type": "Article",
    "title": "Hello World",
    "date": "2016/10/21",
    "content": "你好，世界!"
  }, {
    "type": "Article",
    "title": "Hello World",
    "date": "2016/10/21",
    "content": "你好，世界!"
  }, {
    "type": "Article",
    "title": "Hello World",
    "date": "2016/10/21",
    "content": "你好，世界!"
  }, {
    "type": "Article",
    "title": "Hello World",
    "date": "2016/10/21",
    "content": "你好，世界!"
  }
]